.long_description.md
MANIFEST.in
ReadMe.md
setup.cfg
setup.py
lib/pyyaml_future.egg-info/PKG-INFO
lib/pyyaml_future.egg-info/SOURCES.txt
lib/pyyaml_future.egg-info/dependency_links.txt
lib/pyyaml_future.egg-info/requires.txt
lib/pyyaml_future.egg-info/top_level.txt
lib/yamlfuture/__init__.py
lib/yamlfuture/loader.py
lib/yamlfuture/stdlib.py
lib/yamlfuture/xxx.py
test/test.py