Metadata-Version: 2.1
Name: pyyaml-future
Version: 0.0.6
Summary: Use YAML 1.3 Features in PyYAML (YAML 1.1)
Home-page: https://github.com/yaml/pyyaml-future
Author: Ingy döt Net
Author-email: ingy@ingy.net
License: MIT
Keywords: yaml,future
Platform: UNKNOWN
Classifier: Development Status :: 3 - Alpha
Classifier: Intended Audience :: Developers
Classifier: License :: OSI Approved :: MIT License
Classifier: Programming Language :: Python :: 3
Classifier: Programming Language :: Python :: 3.6
Classifier: Programming Language :: Python :: 3.7
Classifier: Programming Language :: Python :: 3.8
Classifier: Programming Language :: Python :: 3.9
Classifier: Programming Language :: Python :: 3 :: Only
Requires-Python: >=3.6, <4
